.bumpversion.toml
MANIFEST.in
README.md
setup.cfg
setup.py
streamlit_pdf_viewer_plus/__init__.py
streamlit_pdf_viewer_plus.egg-info/PKG-INFO
streamlit_pdf_viewer_plus.egg-info/SOURCES.txt
streamlit_pdf_viewer_plus.egg-info/dependency_links.txt
streamlit_pdf_viewer_plus.egg-info/requires.txt
streamlit_pdf_viewer_plus.egg-info/top_level.txt
streamlit_pdf_viewer_plus/frontend/dist/index.html
streamlit_pdf_viewer_plus/frontend/dist/css/app.a6f03f27.css
streamlit_pdf_viewer_plus/frontend/dist/css/chunk-vendors.ee6905b7.css
streamlit_pdf_viewer_plus/frontend/dist/img/altText_add.7748ee93.svg
streamlit_pdf_viewer_plus/frontend/dist/img/altText_done.1026be11.svg
streamlit_pdf_viewer_plus/frontend/dist/img/cursor-editorFreeHighlight.1fed7bb7.svg
streamlit_pdf_viewer_plus/frontend/dist/img/cursor-editorFreeText.0b596377.svg
streamlit_pdf_viewer_plus/frontend/dist/img/cursor-editorInk.f94c2f42.svg
streamlit_pdf_viewer_plus/frontend/dist/img/cursor-editorTextHighlight.5636640c.svg
streamlit_pdf_viewer_plus/frontend/dist/img/editor-toolbar-delete.6694a89f.svg
streamlit_pdf_viewer_plus/frontend/dist/img/toolbarButton-editorHighlight.c3287eaa.svg
streamlit_pdf_viewer_plus/frontend/dist/img/toolbarButton-menuArrow.37a6145d.svg
streamlit_pdf_viewer_plus/frontend/dist/js/app.99c6acc0.js
streamlit_pdf_viewer_plus/frontend/dist/js/app.99c6acc0.js.map
streamlit_pdf_viewer_plus/frontend/dist/js/chunk-vendors.2fdfabfa.js
streamlit_pdf_viewer_plus/frontend/dist/js/chunk-vendors.2fdfabfa.js.map
streamlit_pdf_viewer_plus/frontend/dist/pdfjs-dist/cmaps/78-EUC-H.bcmap
streamlit_pdf_viewer_plus/frontend/dist/pdfjs-dist/cmaps/78-EUC-V.bcmap
streamlit_pdf_viewer_plus/frontend/dist/pdfjs-dist/cmaps/78-H.bcmap
streamlit_pdf_viewer_plus/frontend/dist/pdfjs-dist/cmaps/78-RKSJ-H.bcmap
streamlit_pdf_viewer_plus/frontend/dist/pdfjs-dist/cmaps/78-RKSJ-V.bcmap
streamlit_pdf_viewer_plus/frontend/dist/pdfjs-dist/cmaps/78-V.bcmap
streamlit_pdf_viewer_plus/frontend/dist/pdfjs-dist/cmaps/78ms-RKSJ-H.bcmap
streamlit_pdf_viewer_plus/frontend/dist/pdfjs-dist/cmaps/78ms-RKSJ-V.bcmap
streamlit_pdf_viewer_plus/frontend/dist/pdfjs-dist/cmaps/83pv-RKSJ-H.bcmap
streamlit_pdf_viewer_plus/frontend/dist/pdfjs-dist/cmaps/90ms-RKSJ-H.bcmap
