Metadata-Version: 2.1
Name: streamlit-pdf-viewer-plus
Version: 0.0.4
Summary: Streamlit component for PDF visualisation and manipulation
Home-page: https://github.com/supercoderhawk/streamlit-pdf-viewer-plus
Author: supercoderhawk
Author-email: supercoderhawk@gmail.com
Requires-Python: >=3.7
Provides-Extra: devel
